<?xml version="1.0" encoding="UTF-8" standalone="no"?>
<cat xmlns="urn:apple:names:siri:cat:1.0" id="addTasksV2#unsupportedTemporalEventTrigger">
  <meta name="category" value="Can't Do"/>
  <meta name="readyForLoc" value="true"/>
  <meta name="muteIfNeeded" value="false"/>
  <meta name="notUseful" value="false"/>
  <meta name="description" value="Executed when the temporalEventTrigger slot is unsupported."/>
  <parameters>
    <parameter name="unsupportedValue" type="dialog.String"/>
    <parameter name="unsupportedReason" type="dialog.Number"/>
    <parameter name="slotName" type="dialog.String"/>
    <parameter name="appName" type="dialog.String"/>
    <parameter name="device" type="sirikit.DeviceState"/>
  </parameters>
</cat>
